{
	"button":{
	   "dong_y":{
		  "x":100,
		  "y":200
	   },
	   "xac_nhan":{
		  "x":100,
		  "y":200
	   },
	   "xac_nhan_event":{
		  "x":100,
		  "y":200
	   },
	   "event_button":{
		  "x":100,
		  "y":200
	   },
	   "event_lvl_button":{
		  "x":100,
		  "y":200
	   },
	   "icon_event_common":{
		"x":100,
		"y":200
		},
	   "event_arena_button":{
		  "x":100,
		  "y":200
	   },
	   "event_devil":{
		  "move_check_npc_x":483,
		  "move_check_npc_y":371
	   },
	   "event_devil_icon":{
		  "x":23,
		  "y":251,
		  "chap_nhan_x":476,
		  "chap_nhan_y":476,
		  "huy_bo_x":554,
		  "huy_bo_y":475,
		  "devil_3_x":843,
		  "devil_3_y":409,
		  "devil_4_x":789,
		  "devil_4_y":460,
		  "devil_5_x":830,
		  "devil_5_y":515,
		  "devil_6_x":809,
		  "devil_6_y":567
	   },"event_devil_icon_no_had_k":{
		  "x":37,
		  "y":171,
		  "chap_nhan_x":476,
		  "chap_nhan_y":476,
		  "huy_bo_x":554,
		  "huy_bo_y":475,
		  "devil_3_x":843,
		  "devil_3_y":409
	   }
	},
	"web":{
	   "console_tab":{
		  "x":174,
		  "y":613
	   },
	   "button_clean_console":{
		  "x":44,
		  "y":638
	   },
	   "input_text_dien_dan":{
		  "x":582,
		  "y":281
	   },
	   "button_send_dien_dan":{
		  "x":1372,
		  "y":367
	   }
	},
	"zalo":{
	   "tim_kiem_button":{
		  "x":196,
		  "y":162
	   },
	   "ket_qua_tim_kiem":{
		  "x":192,
		  "y":335
	   }
	},
	"event":{
	   "event_button":{
		  "x":100,
		  "y":200
	   },
	   "event_lvl_button":{
		  "x":100,
		  "y":200
	   },
	   "event_arena_button":{
		  "x":100,
		  "y":200
	   }
	},
	"follow":{
	   "leader":{
		  "x":100,
		  "y":200
	   },
	   "person_second":{
		  "x":100,
		  "y":200
	   }
	},
	"position":{
	   "arena_time":{
		  "x":100,
		  "y":200
	   },
	   "person_second":{
		  "x":100,
		  "y":200
	   }
	},
	"color":{
	   "arena_time":"0xFFFFFF",
	   "person_second":{
		  "x":100,
		  "y":200
	   }
	},
	"follow_leader":{
	   "position_1_x":995,
	   "position_1_y":147
	},
	"event_icon":{
	   "x":157,
	   "y":119,
	   "map_lvl_x":484,
	   "map_lvl_y":326,
	   "map_lvl_center_x":399,
	   "map_lvl_center_y":183,
	   "map_stadium_x":503,
	   "map_stadium_y":493
	},
	"move":{
	   "other_map_x":161,
	   "other_map_y":297
	},
	"change_char":{
	   "x":518,
	   "y":456
	},
	"switch_char":{
	   "icon_x":999,
	   "icon_y":671,
	   "button_change_x":560,
	   "button_change_y":512
	},
	"screen_mouse_move":{
	   "center_x":504,
	   "center_y":361
	},
	"close_shop":{
	   "x":327,
	   "y":104
	},
	"close_chao":{
	   "x":508,
	   "y":526
	}
 }